meson_build/meson-logs/meson-log.txt
meson_build/meson-private/cmd_line.txt
meson_build/meson-private/pycompile.py
meson_build/meson-private/sanitycheckc.exe
meson_build/meson-private/sanitycheckf.exe
meson_build/pyhams/_hams.cpython-311-x86_64-linux-musl.so
pyhams/__init__.py
pyhams/_hams.cpython-310-x86_64-linux-gnu.so
pyhams/_hams.cpython-311-x86_64-linux-musl.so
pyhams/_hams.cpython-39-x86_64-linux-gnu.so
pyhams/pyhams.py
pyhams.libs/libgcc_s-0cd532bd.so.1
pyhams.libs/libgfortran-2c33b284.so.5.0.0
pyhams.libs/libgomp-8949ffbe.so.1.0.0
pyhams.libs/libquadmath-bb76a5fc.so.0.0.0
pyhams-1.3.1.dist-info/METADATA
pyhams-1.3.1.dist-info/WHEEL
pyhams-1.3.1.dist-info/top_level.txt
pyhams-1.3.1.dist-info/RECORD
pyhams-1.3.1.dist-info/licenses/LICENSE
