Metadata-Version: 2.4
Name: pyHAMS
Version: 1.3.1
Summary: Python module wrapping around HAMS
Author-email: NREL WISDEM Team <systems.engineering@nrel.gov>
Maintainer-email: NREL WISDEM Team <systems.engineering@nrel.gov>
License: Apache-2.0
Project-URL: homepage, https://github.com/WISDEM/pyHAMS
Project-URL: documentation, https://github.com/YingyiLiu/HAMS
Project-URL: source, https://github.com/WISDEM/pyHAMS
Project-URL: download, https://github.com/WISDEM/pyHAMS/releases
Project-URL: tracker, https://github.com/WISDEM/pyHAMS/issues
Keywords: wind,turbine,mdao,design,optimization
Classifier: Development Status :: 4 - Beta
Classifier: Intended Audience :: Science/Research
Classifier: Topic :: Scientific/Engineering
Classifier: License :: OSI Approved :: Apache Software License
Classifier: Programming Language :: Python :: 3
Classifier: Programming Language :: Python :: 3.9
Classifier: Programming Language :: Python :: 3.10
Classifier: Programming Language :: Python :: 3.11
Classifier: Programming Language :: Python :: 3.12
Classifier: Programming Language :: Python :: 3.13
Classifier: Programming Language :: Python :: 3.14
Classifier: Programming Language :: Python :: 3 :: Only
Classifier: Programming Language :: Fortran
Classifier: Operating System :: Microsoft :: Windows
Classifier: Operating System :: POSIX :: Linux
Classifier: Operating System :: POSIX
Classifier: Operating System :: Unix
Classifier: Operating System :: MacOS
Requires-Python: >=3.9
License-File: LICENSE
Requires-Dist: numpy
Requires-Dist: meson
Requires-Dist: ninja
Provides-Extra: test
Requires-Dist: pytest; extra == "test"
Dynamic: license-file
